[{"division":[""],"name":"Eduardo Mondlane University","shortName":"Universidade Eduardo Mondlane (UEM)"},{"division":[""],"name":"Alberto Chipande Institute of Science and Technology","shortName":"Instituto Superior de Ciências e Tecnologia Alberto Chipande"},{"division":[""],"name":"Catholic University of Mozambique","shortName":"Universidade Católica de Moçambique (UCM)"},{"division":[""],"name":"Don Bosco Institute of Science and Management","shortName":"Instituto Superior Dom Bosco (ISDB)"},{"division":[""],"name":"Gaza Polytechnic Institute","shortName":"Instituto Superior Politécnico de Gaza – Campus Politecnico, Chókwe (ISPG)"},{"division":[""],"name":"Institute of Art and Culture","shortName":"Instituto Superior de Artes e Cultura (ISArC)"},{"division":[""],"name":"Institute of Business Management","shortName":"Instituto Superior de Gestão de Negócios (ISGN)"},{"division":[""],"name":"Institute of Communication and Image Studies","shortName":"Instituto Superior de Comunicação e Imagem (ISCIM)"},{"division":[""],"name":"Institute of Education and Technology - One World University","shortName":"Instituto Superior de Educação e Tecnologia - One World University (ISET/OWU)"},{"division":[""],"name":"Institute of Health Sciences","shortName":"Instituto Superior de Ciências de Saúde (ISCISA)"},{"division":[""],"name":"Institute of International Relations","shortName":"Instituto Superior de Relações Internacionais (ISRI)"},{"division":[""],"name":"Institute of Local Studies and Development","shortName":"Instituto Superior de Estudos e Desenvolvimento Local (ISEDEL)"},{"division":[""],"name":"Institute of Management, Business and Education","shortName":"Instituto Superior de Gestão, Administração e Educação (ISG)"},{"division":[""],"name":"Institute of Management, Business and Finance","shortName":"Instituto Superior de Gestão, Comércio e Finanças (ISGECOF)"},{"division":[""],"name":"Institute of Public Administration","shortName":"Instituto Superior de Administração Pública (ISAP)"},{"division":[""],"name":"Institute of Science and Management","shortName":"Instituto Superior de Ciência e Gestão (INSCIG)"},{"division":[""],"name":"Institute of Technology and Management","shortName":"Instituto Superior de Tecnologia e Gestão (ISTEG)"},{"division":[""],"name":"Institute of Training, Research and Science","shortName":"Instituto Superior de Formação, Investigação e Ciência (ISFIC)"},{"division":[""],"name":"Institute of Transport and Communications","shortName":"Instituto Superior de Transportes e Comunicações (ISUTC)"},{"division":[""],"name":"Jean Piaget University of Mozambique","shortName":"Universidade Jean Piaget de Moçambique (UJPM)"},{"division":[""],"name":"Lurio University","shortName":"Universidade Lúrio"},{"division":[""],"name":"Manica Polytechnic Institute","shortName":"Instituto Superior Politécnico de Manica (ISPM)"},{"division":[""],"name":"Monitor Institute","shortName":"Instituto Superior Monitor (ISM)"},{"division":[""],"name":"Mother Mary Africa Institute","shortName":"Instituto Superior Maria Mãe de África (ISMMA)"},{"division":[""],"name":"Mozambique Institute of Accountancy and Auditing","shortName":"Instituto Superior de Contabilidade e Auditoria de Moçambique (ISCAM)"},{"division":[""],"name":"Mozambique Institute of Science and Technology","shortName":"Instituto Superior de Ciências e Tecnologia de Moçambique (ISCTEM)"},{"division":[""],"name":"Mussa Bin Bique University","shortName":"Universidade Mussa Bin Bique (UMBB)"},{"division":[""],"name":"Mutasa Institute","shortName":"Instituto Superior Mutasa (ISMU)"},{"division":[""],"name":"Nachingwea University","shortName":"Universidade Nachingwea (UNA)"},{"division":[""],"name":"Pedagogical University","shortName":"Universidade Pedagógica (UP)"},{"division":[""],"name":"Polytechnic University","shortName":"Universidade Politécnica"},{"division":[""],"name":"Saint Thomas University of Mozambique","shortName":"Universidade São Tomás de Moçambique"},{"division":[""],"name":"School of Corporate and Social Management","shortName":"Escola Superior de Gestão Corporativa e Social (ESGCS)"},{"division":[""],"name":"School of Economics and Management","shortName":"Escola Superior de Economia e Gestão (ESEG)"},{"division":[""],"name":"School of Journalism","shortName":"Escola Superior de Jornalismo (ESJ)"},{"division":[""],"name":"School of Nautical Sciences","shortName":"Escola Superior de Ciências Náuticas"},{"division":[""],"name":"Songo Polytechnic Institute","shortName":"Instituto Superior Politécnico de Songo (ISPS)"},{"division":[""],"name":"Technical University of Mozambique","shortName":"Universidade Técnica de Moçambique"},{"division":[""],"name":"Tete Polytechnic Institute","shortName":"Instituto Superior Politécnico de Tete (ISPT)"},{"division":[""],"name":"Zambeze University","shortName":"Universidade Zambeze – Unizambeze (UZ)"}]